mhyy/__init__.py
mhyy/_api.py
mhyy/_client.py
mhyy/_exceptions.py
mhyy/_features.py
mhyy/_notification.py
mhyy/_types.py
mhyy/_user.py
mhyy/_wallet.py
mhyy.py-3.1.0.dist-info/LICENSE
mhyy.py-3.1.0.dist-info/METADATA
mhyy.py-3.1.0.dist-info/WHEEL
mhyy.py-3.1.0.dist-info/top_level.txt
mhyy.py-3.1.0.dist-info/RECORD
