Metadata-Version: 2.1
Name: mhyy.py
Version: 3.1.0
Summary: Python API for miHoYo Cloud Gaming (Genshin Impact Cloud, Honkai:StarRail Cloud, Zenless Zone Zero Cloud)
Author-email: GuangChen2333 <guangchenworks@outlook.com>
Project-URL: Homepage, https://github.com/GuangChen2333/mhyy.py
Project-URL: Bug Tracker, https://github.com/GuangChen2333/mhyy.py/issues
Classifier: Programming Language :: Python :: 3
Classifier: License :: OSI Approved :: BSD License
Classifier: Operating System :: OS Independent
Requires-Python: >=3.8
License-File: LICENSE
Requires-Dist: httpx
Requires-Dist: dataclasses-json
